ph_baseliner/__init__.py
ph_baseliner/codes/ECCCNYS_2020.json
ph_baseliner/codes/__init__.py
ph_baseliner/codes/lighting_space_types.py
ph_baseliner/codes/model.py
ph_baseliner/codes/options.py
ph_baseliner/phpp/__init__.py
ph_baseliner/phpp/areas.py
ph_baseliner/phpp/components.py
ph_baseliner/phpp/lighting.py
ph_baseliner/phpp/u_values.py
ph_baseliner/phpp/windows.py
ph_baseliner/phx/__init__.py
ph_baseliner/phx/areas.py
ph_baseliner/phx/constructions.py
ph_baseliner/phx/lighting.py
ph_baseliner/phx/windows.py
PH_Baseliner-1.3.2.dist-info/LICENSE
PH_Baseliner-1.3.2.dist-info/METADATA
PH_Baseliner-1.3.2.dist-info/WHEEL
PH_Baseliner-1.3.2.dist-info/top_level.txt
PH_Baseliner-1.3.2.dist-info/RECORD
