Metadata-Version: 2.1
Name: PH-Baseliner
Version: 1.3.2
Summary: Tools to automatically setup the code-minimum Baseline values for Passive House models.
Home-page: https://github.com/PH-Tools/PH_Baseliner
Author: PH-Tools
Author-email: phtools@bldgtyp.com
License: GPLv3+
Classifier: Programming Language :: Python :: 3
Classifier: Programming Language :: Python :: 3.10
Classifier: Programming Language :: Python :: Implementation :: CPython
Classifier: License :: OSI Approved :: GNU General Public License v3 or later (GPLv3+)
Classifier: Operating System :: OS Independent
Classifier: Typing :: Typed
License-File: LICENSE
